graphex/__init__.py
graphex/__main__.py
graphex/compositeGraphInput.py
graphex/config.py
graphex/constants.py
graphex/datatype.py
graphex/exceptions.py
graphex/fields.py
graphex/git_resolution.py
graphex/graph.py
graphex/graphfile.py
graphex/inventory.py
graphex/log.py
graphex/node.py
graphex/plugin_doc_generator.py
graphex/registry.py
graphex/runtime.py
graphex/server.py
graphex/util.py
graphex/vault.py
graphex/data/__init__.py
graphex/data/primitives.py
graphex/data/visualization_graphs.py
graphex/nodes/__init__.py
graphex/nodes/comment.py
graphex/nodes/conditionals.py
graphex/nodes/datacontainer.py
graphex/nodes/exceptions.py
graphex/nodes/files.py
graphex/nodes/graph.py
graphex/nodes/json.py
graphex/nodes/lists.py
graphex/nodes/loops.py
graphex/nodes/math.py
graphex/nodes/network.py
graphex/nodes/pathing.py
graphex/nodes/rand.py
graphex/nodes/regex.py
graphex/nodes/strings.py
graphex/nodes/subprocess.py
graphex/nodes/templates.py
graphex/nodes/threads.py
graphex/nodes/time.py
graphex/nodes/utility.py
graphex/nodes/variables.py
graphex/nodes/visualizations.py
graphex/nodes/zipfile.py
graphex/sockets/__init__.py
graphex/sockets/base.py
graphex/sockets/input_sockets.py
graphex/sockets/output_sockets.py
graphex/website/favicon.ico
graphex/website/index.html
graphex/website/logo.png
graphex/website/assets/index-73587689.js
graphex/website/assets/index-b700a260.css
graphex/website/assets/material-icons-8265f647.woff2
graphex/website/assets/material-icons-fd84f88b.woff
graphex/website/assets/material-icons-outlined-35dca8a7.woff2
graphex/website/assets/material-icons-outlined-8e94758c.woff
graphex/website/assets/material-icons-round-1c135b15.woff
graphex/website/assets/material-icons-round-c948f126.woff2
graphex/website/assets/material-icons-sharp-d31bfb81.woff2
graphex/website/assets/material-icons-sharp-fa3888ef.woff
graphex/website/assets/material-icons-two-tone-1e673ba8.woff2
graphex/website/assets/material-icons-two-tone-3d34f30a.woff
mitre_graphex-1.16.4.dist-info/licenses/LICENSE
mitre_graphex-1.16.4.dist-info/METADATA
mitre_graphex-1.16.4.dist-info/WHEEL
mitre_graphex-1.16.4.dist-info/top_level.txt
mitre_graphex-1.16.4.dist-info/RECORD
