Metadata-Version: 2.4
Name: mitre-graphex
Version: 1.16.4
Summary: Visual programming tool for environment automation.
Author: The MITRE Corporation
Requires-Python: >=3.10
License-File: LICENSE
Requires-Dist: build
Requires-Dist: cryptography
Requires-Dist: flask-socketio>=5.3.4
Requires-Dist: flask>=2.2.3
Requires-Dist: gitPython==3.1.*
Requires-Dist: matplotlib
Requires-Dist: networkx
Requires-Dist: numpy
Requires-Dist: ping3==4.0.4
Requires-Dist: pyopenssl
Requires-Dist: python-dateutil==2.8.2
Requires-Dist: pyyaml>=6.0.1
Requires-Dist: requests>=2.31.0
Requires-Dist: service_identity
Requires-Dist: typeguard>=4.0.0
Requires-Dist: typing-extensions>=4.7.1
Requires-Dist: wheel
Dynamic: author
Dynamic: license-file
Dynamic: requires-dist
Dynamic: requires-python
Dynamic: summary
